{
  "project_info": {
    "project_number": "633489039935",
    "firebase_url": "https://utility-monitoring-poc.firebaseio.com",
    "project_id": "utility-monitoring-poc",
    "storage_bucket": "utility-monitoring-poc.appspot.com"
  },
  "client": [
    {
      "client_info": {
        "mobilesdk_app_id": "1:633489039935:android:96ab31e3f1cbcaafa08e8a",
        "android_client_info": {
          "package_name": "com.example.utilitymanagement"
        }
      },
      "oauth_client": [
        {
          "client_id": "633489039935-catduam0t4fiv2j0496rol12o6cpdppj.apps.googleusercontent.com",
          "client_type": 1,
          "android_info": {
            "package_name": "com.example.utilitymanagement",
            "certificate_hash": "93d1b566758675d46432c8a301b57bb0035b96b6"
          }
        },
        {
          "client_id": "633489039935-n77v258ksohhpp6db3f22ug3u2ghsdsl.apps.googleusercontent.com",
          "client_type": 3
        }
      ],
      "api_key": [
        {
          "current_key": "AIzaSyCU0S1G0e1RuZ_UEG3_20LbSX1t_fWdRxQ"
        }
      ],
      "services": {
        "appinvite_service": {
          "other_platform_oauth_client": [
            {
              "client_id": "633489039935-n77v258ksohhpp6db3f22ug3u2ghsdsl.apps.googleusercontent.com",
              "client_type": 3
            }
          ]
        }
      }
    }
  ],
  "configuration_version": "1"
}